{
  "generated_at": "2026-05-16T15:13:35Z",
  "status": "imported",
  "source": "reep",
  "source_license": "CC0-1.0",
  "source_version": "2026.17",
  "source_people_csv": "/Users/chamcham/Downloads/people.csv",
  "source_names_csv": "/Users/chamcham/Downloads/reep-names.csv",
  "source_rows": 444707,
  "source_alias_rows": 27591,
  "manual_patch": "/Users/chamcham/Documents/AI/CODEX/soccer/football-data-platform/data/patches/person_id_map.manual.json",
  "manual_overrides_applied": 11,
  "players_considered": 208,
  "rows_written": 208,
  "counts": {
    "exact_unique": 205,
    "ambiguous": 0,
    "missing": 3
  },
  "coverage": {
    "matched_count": 205,
    "unambiguous_count": 205,
    "ambiguous_count": 0,
    "missing_count": 3,
    "hit_rate": 0.985577,
    "unambiguous_rate": 0.985577
  },
  "outputs": {
    "normalized": "/Users/chamcham/Documents/AI/CODEX/soccer/football-data-platform/data/normalized/person_id_map_master.json",
    "unresolved_report": "/Users/chamcham/Documents/AI/CODEX/soccer/football-data-platform/reports/person_id_map_unresolved_report.json"
  },
  "notes": [
    "This import writes an ID map only; it does not overwrite FIFA/FA roster facts.",
    "Ambiguous rows require DOB, club, provider ID, or manual review before use as high-confidence mappings."
  ]
}
